setup.py
c4/utils/__init__.py
c4_utils.egg-info/PKG-INFO
c4_utils.egg-info/SOURCES.txt
c4_utils.egg-info/dependency_links.txt
c4_utils.egg-info/requires.txt
c4_utils.egg-info/top_level.txt