Metadata-Version: 2.1
Name: c4-utils
Version: 0.0.2
Summary: c4.utils
Author: QA Automation
Classifier: Programming Language :: Python :: 3
Requires-Dist: mss==3.0.1; python_version < "3.5"
Requires-Dist: mss==6.1.0; python_version >= "3.5"
